fmpsdk/__init__.py
fmpsdk/alternative_data.py
fmpsdk/calendar.py
fmpsdk/commodities.py
fmpsdk/company_valuation.py
fmpsdk/cryptocurrencies.py
fmpsdk/etf.py
fmpsdk/euronext.py
fmpsdk/forex.py
fmpsdk/general.py
fmpsdk/insider_trading.py
fmpsdk/institutional_fund.py
fmpsdk/market_indexes.py
fmpsdk/mutual_funds.py
fmpsdk/senate.py
fmpsdk/settings.py
fmpsdk/shares_float.py
fmpsdk/stock_market.py
fmpsdk/stock_time_series.py
fmpsdk/technical_indicators.py
fmpsdk/tsx.py
fmpsdk/url_methods.py
fmpsdk-20240209.0.dist-info/LICENSE.md
fmpsdk-20240209.0.dist-info/METADATA
fmpsdk-20240209.0.dist-info/WHEEL
fmpsdk-20240209.0.dist-info/RECORD
