Metadata-Version: 2.1
Name: fmpsdk
Version: 20240209.0
Summary: 
Author: Dax Mickelson
Author-email: github@daxm.net
Requires-Python: >=3.11,<4.0
Classifier: Programming Language :: Python :: 3
Classifier: Programming Language :: Python :: 3.11
Classifier: Programming Language :: Python :: 3.12
Requires-Dist: python-dotenv
Requires-Dist: requests
